connexion_buzz/__init__.py
connexion_buzz-0.2.1.dist-info/METADATA
connexion_buzz-0.2.1.dist-info/WHEEL
connexion_buzz-0.2.1.dist-info/top_level.txt
connexion_buzz-0.2.1.dist-info/RECORD
