Metadata-Version: 2.1
Name: connexion-buzz
Version: 0.2.1
Summary: py-buzz bindings specifically for connexion applications
Home-page: https://gitlab.mytradingdata.com/common/connexion-buzz
Author: Aleksey Dalekin
Author-email: ald@investex.com
License: UNKNOWN
Keywords: connexion error py-buzz
Platform: UNKNOWN
Classifier: Development Status :: 3 - Alpha
Classifier: Intended Audience :: Developers
Classifier: Programming Language :: Python :: 3.5
Classifier: Programming Language :: Python :: 3.6
Classifier: Programming Language :: Python :: 3.7
Classifier: Topic :: Software Development :: Libraries
Requires-Dist: connexion (>=2.0.0)
Requires-Dist: py-buzz (>=0.3.6)
